[
    {
        "internal": "wood",
        "name": "Wood",
        "type": "Material",
        "description": "Obtained from woodcutting.",
        "value": 1
    },
    {
        "internal": "fish",
        "name": "Fish",
        "type": "Heal",
        "description": "Obtained from fishing.",
        "value": 1.3,
        "heal": 0.25
    },
    {
        "internal": "rock",
        "name": "Rock",
        "type": "Material",
        "description": "What you usually find when you go mining.",
        "value": 0.25
    },
    {
        "internal": "iron",
        "name": "Iron",
        "type": "Material",
        "description": "You can sometimes find this when mining.",
        "value": 2
    },
    {
        "internal": "diamond",
        "name": "Diamond",
        "type": "Material",
        "description": "A rare find for a miner.",
        "value": 15
    },
    {
        "internal": "strengonine",
        "name": "Strengonine",
        "type": "Material",
        "description": "An extremely strong and rare mineral found underground.",
        "value": 35
    }
]